aztools/__init__.py
aztools/_version.py
aztools/data.py
aztools/lcurve.py
aztools/misc.py
aztools/simlc.py
aztools/scripts/ogrppha.py
aztools-0.3.9.dist-info/licenses/LICENSE
aztools-0.3.9.dist-info/METADATA
aztools-0.3.9.dist-info/WHEEL
aztools-0.3.9.dist-info/entry_points.txt
aztools-0.3.9.dist-info/top_level.txt
aztools-0.3.9.dist-info/RECORD
